pyjt/ComponentFinder.py
pyjt/Errors.py
pyjt/Fixture.py
pyjt/Frame.py
pyjt/Inspector.py
pyjt/Proxy.py
pyjt/Robot.py
pyjt/__init__.py
pyjt-0.6.0.dist-info/LICENSE
pyjt-0.6.0.dist-info/METADATA
pyjt-0.6.0.dist-info/WHEEL
pyjt-0.6.0.dist-info/top_level.txt
pyjt-0.6.0.dist-info/RECORD
